pycomscore/__init__.py
pycomscore/pycomscore.py
pycomscore/test.py
pycomscore-0.0.5.dist-info/LICENSE
pycomscore-0.0.5.dist-info/METADATA
pycomscore-0.0.5.dist-info/WHEEL
pycomscore-0.0.5.dist-info/top_level.txt
pycomscore-0.0.5.dist-info/RECORD
